[
  {
    "id": "cmndoblhe0006js6x8kqrfrx1",
    "dayIdx": 0,
    "timeIdx": 0,
    "title": "Umum",
    "color": "emerald",
    "formattedTime": "17:00-23:00",
    "registrationTime": "16:00",
    "extra": null,
    "disabledDates": null,
    "statusOverride": null,
    "doctorId": "cmndoblgr0005js6xysq45w70"
  },
  {
    "id": "cmndobli40007js6xpx1at13o",
    "dayIdx": 2,
    "timeIdx": 0,
    "title": "Umum",
    "color": "emerald",
    "formattedTime": "17:00-23:00",
    "registrationTime": "16:00",
    "extra": null,
    "disabledDates": null,
    "statusOverride": null,
    "doctorId": "cmndoblgr0005js6xysq45w70"
  },
  {
    "id": "cmndoblim0008js6xr19w4tch",
    "dayIdx": 4,
    "timeIdx": 0,
    "title": "Umum",
    "color": "emerald",
    "formattedTime": "17:00-23:00",
    "registrationTime": "16:00",
    "extra": null,
    "disabledDates": null,
    "statusOverride": null,
    "doctorId": "cmndoblgr0005js6xysq45w70"
  },
  {
    "id": "cmndobljk000ajs6xk3zz64kn",
    "dayIdx": 1,
    "timeIdx": 0,
    "title": "Umum",
    "color": "emerald",
    "formattedTime": "10:00-12:00",
    "registrationTime": "09:00",
    "extra": null,
    "disabledDates": null,
    "statusOverride": null,
    "doctorId": "cmndobliy0009js6xogimf9xc"
  },
  {
    "id": "cmndoblk6000bjs6xkik474ne",
    "dayIdx": 3,
    "timeIdx": 0,
    "title": "Umum",
    "color": "emerald",
    "formattedTime": "10:00-12:00",
    "registrationTime": "09:00",
    "extra": null,
    "disabledDates": null,
    "statusOverride": null,
    "doctorId": "cmndobliy0009js6xogimf9xc"
  },
  {
    "id": "cmndoblkh000cjs6xqkxzsg6u",
    "dayIdx": 5,
    "timeIdx": 0,
    "title": "Umum",
    "color": "emerald",
    "formattedTime": "10:00-12:00",
    "registrationTime": "09:00",
    "extra": null,
    "disabledDates": null,
    "statusOverride": null,
    "doctorId": "cmndobliy0009js6xogimf9xc"
  },
  {
    "id": "cmndobllp000ejs6xcmlcm8w7",
    "dayIdx": 0,
    "timeIdx": 0,
    "title": "Obstetri & Ginekologi",
    "color": "blue",
    "formattedTime": "10:00-12:00",
    "registrationTime": "09:00",
    "extra": null,
    "disabledDates": null,
    "statusOverride": null,
    "doctorId": "cmndobll4000djs6xph56wyp2"
  },
  {
    "id": "cmndoblm0000fjs6xbbtc0md1",
    "dayIdx": 2,
    "timeIdx": 0,
    "title": "Obstetri & Ginekologi",
    "color": "blue",
    "formattedTime": "10:00-12:00",
    "registrationTime": "09:00",
    "extra": null,
    "disabledDates": null,
    "statusOverride": null,
    "doctorId": "cmndobll4000djs6xph56wyp2"
  },
  {
    "id": "cmndoblmb000gjs6xt433qff4",
    "dayIdx": 4,
    "timeIdx": 0,
    "title": "Obstetri & Ginekologi",
    "color": "blue",
    "formattedTime": "10:00-12:00",
    "registrationTime": "09:00",
    "extra": null,
    "disabledDates": null,
    "statusOverride": null,
    "doctorId": "cmndobll4000djs6xph56wyp2"
  },
  {
    "id": "cmndoblqo000pjs6x0ntrokde",
    "dayIdx": 0,
    "timeIdx": 0,
    "title": "Anak",
    "color": "emerald",
    "formattedTime": "15:00-18:00",
    "registrationTime": "14:00",
    "extra": null,
    "disabledDates": null,
    "statusOverride": null,
    "doctorId": "cmndoblqc000ojs6xuywmmnkl"
  },
  {
    "id": "cmndoblrk000rjs6x6m5et5id",
    "dayIdx": 2,
    "timeIdx": 0,
    "title": "Anak",
    "color": "emerald",
    "formattedTime": "15:00-18:00",
    "registrationTime": "14:00",
    "extra": null,
    "disabledDates": null,
    "statusOverride": null,
    "doctorId": "cmndoblqc000ojs6xuywmmnkl"
  },
  {
    "id": "cmndoblrv000sjs6x81hpt09v",
    "dayIdx": 3,
    "timeIdx": 0,
    "title": "Anak",
    "color": "emerald",
    "formattedTime": "15:00-18:00",
    "registrationTime": "14:00",
    "extra": null,
    "disabledDates": null,
    "statusOverride": null,
    "doctorId": "cmndoblqc000ojs6xuywmmnkl"
  },
  {
    "id": "cmndoblua000wjs6x689d9t42",
    "dayIdx": 0,
    "timeIdx": 1,
    "title": "Bedah Umum",
    "color": "blue",
    "formattedTime": "14:00-17:00",
    "registrationTime": "13:00",
    "extra": null,
    "disabledDates": null,
    "statusOverride": null,
    "doctorId": "cmndoblt3000ujs6x1qraknzo"
  },
  {
    "id": "cmndoblva000yjs6xxq4ff20i",
    "dayIdx": 1,
    "timeIdx": 1,
    "title": "Bedah Umum",
    "color": "blue",
    "formattedTime": "14:00-17:00",
    "registrationTime": "13:00",
    "extra": null,
    "disabledDates": null,
    "statusOverride": null,
    "doctorId": "cmndoblt3000ujs6x1qraknzo"
  },
  {
    "id": "cmndoblvw0010js6xyskehgh2",
    "dayIdx": 2,
    "timeIdx": 1,
    "title": "Bedah Umum",
    "color": "blue",
    "formattedTime": "14:00-17:00",
    "registrationTime": "13:00",
    "extra": null,
    "disabledDates": null,
    "statusOverride": null,
    "doctorId": "cmndoblt3000ujs6x1qraknzo"
  },
  {
    "id": "cmndoblwi0012js6xowljkc8q",
    "dayIdx": 3,
    "timeIdx": 1,
    "title": "Bedah Umum",
    "color": "blue",
    "formattedTime": "14:00-17:00",
    "registrationTime": "13:00",
    "extra": null,
    "disabledDates": null,
    "statusOverride": null,
    "doctorId": "cmndoblt3000ujs6x1qraknzo"
  },
  {
    "id": "cmndoblxf0014js6xlqgdhohu",
    "dayIdx": 4,
    "timeIdx": 1,
    "title": "Bedah Umum",
    "color": "blue",
    "formattedTime": "13:00-17:00",
    "registrationTime": "12:00",
    "extra": null,
    "disabledDates": null,
    "statusOverride": null,
    "doctorId": "cmndoblt3000ujs6x1qraknzo"
  },
  {
    "id": "cmndoblyz0017js6xncypq0tx",
    "dayIdx": 1,
    "timeIdx": 0,
    "title": "Penyakit Dalam",
    "color": "emerald",
    "formattedTime": "14:30-17:00",
    "registrationTime": "13:30",
    "extra": null,
    "disabledDates": null,
    "statusOverride": null,
    "doctorId": "cmndoblyo0016js6xt5mk5h1m"
  },
  {
    "id": "cmndoblza0018js6xpp045lqi",
    "dayIdx": 4,
    "timeIdx": 0,
    "title": "Penyakit Dalam",
    "color": "emerald",
    "formattedTime": "13:30-16:00",
    "registrationTime": "12:30",
    "extra": null,
    "disabledDates": null,
    "statusOverride": null,
    "doctorId": "cmndoblyo0016js6xt5mk5h1m"
  },
  {
    "id": "cmndobm14001bjs6xvd30gxym",
    "dayIdx": 0,
    "timeIdx": 1,
    "title": "Penyakit Dalam",
    "color": "emerald",
    "formattedTime": "18:00-20:00",
    "registrationTime": "17:00",
    "extra": null,
    "disabledDates": null,
    "statusOverride": null,
    "doctorId": "cmndoblzx0019js6xoa7wqajj"
  },
  {
    "id": "cmndobm1r001djs6xi3ibpqw3",
    "dayIdx": 1,
    "timeIdx": 1,
    "title": "Penyakit Dalam",
    "color": "emerald",
    "formattedTime": "18:00-20:00",
    "registrationTime": "17:00",
    "extra": null,
    "disabledDates": null,
    "statusOverride": null,
    "doctorId": "cmndoblzx0019js6xoa7wqajj"
  },
  {
    "id": "cmndobm2d001fjs6x4blsytne",
    "dayIdx": 2,
    "timeIdx": 1,
    "title": "Penyakit Dalam",
    "color": "emerald",
    "formattedTime": "18:00-20:00",
    "registrationTime": "17:00",
    "extra": null,
    "disabledDates": null,
    "statusOverride": null,
    "doctorId": "cmndoblzx0019js6xoa7wqajj"
  },
  {
    "id": "cmndobm31001hjs6x00511x12",
    "dayIdx": 3,
    "timeIdx": 1,
    "title": "Penyakit Dalam",
    "color": "emerald",
    "formattedTime": "18:00-21:00",
    "registrationTime": "17:00",
    "extra": null,
    "disabledDates": null,
    "statusOverride": null,
    "doctorId": "cmndoblzx0019js6xoa7wqajj"
  },
  {
    "id": "cmndoblup000xjs6xlv0lch0g",
    "dayIdx": 1,
    "timeIdx": 0,
    "title": "Bedah Umum",
    "color": "blue",
    "formattedTime": "06:00-07:30",
    "registrationTime": "06:00",
    "extra": null,
    "disabledDates": [],
    "statusOverride": null,
    "doctorId": "cmndoblt3000ujs6x1qraknzo"
  },
  {
    "id": "cmndoblw60011js6x0xhreqgk",
    "dayIdx": 3,
    "timeIdx": 0,
    "title": "Bedah Umum",
    "color": "blue",
    "formattedTime": "06:00-07:30",
    "registrationTime": "06:00",
    "extra": null,
    "disabledDates": null,
    "statusOverride": null,
    "doctorId": "cmndoblt3000ujs6x1qraknzo"
  },
  {
    "id": "cmndoblfo0003js6xmhur4cf7",
    "dayIdx": 3,
    "timeIdx": 0,
    "title": "Obstetri & Ginekologi",
    "color": "blue",
    "formattedTime": "13:15-15:15",
    "registrationTime": "13:05",
    "extra": null,
    "disabledDates": null,
    "statusOverride": null,
    "doctorId": "cmndobldf0000js6xdbpgturi"
  },
  {
    "id": "cmndoblnk000jjs6xh30hnwtu",
    "dayIdx": 1,
    "timeIdx": 0,
    "title": "Anak",
    "color": "emerald",
    "formattedTime": "08:30-13:00",
    "registrationTime": "07:30",
    "extra": null,
    "disabledDates": null,
    "statusOverride": null,
    "doctorId": "cmndoblmp000hjs6xvuue1gw8"
  },
  {
    "id": "cmndobln9000ijs6xwbulqql0",
    "dayIdx": 0,
    "timeIdx": 0,
    "title": "Anak",
    "color": "emerald",
    "formattedTime": "08:30-13:00",
    "registrationTime": "07:30",
    "extra": null,
    "disabledDates": null,
    "statusOverride": null,
    "doctorId": "cmndoblmp000hjs6xvuue1gw8"
  },
  {
    "id": "cmndobltf000vjs6xmeq2nobz",
    "dayIdx": 0,
    "timeIdx": 0,
    "title": "Bedah Umum",
    "color": "blue",
    "formattedTime": "06:00-07:30",
    "registrationTime": "06:00",
    "extra": null,
    "disabledDates": null,
    "statusOverride": null,
    "doctorId": "cmndoblt3000ujs6x1qraknzo"
  },
  {
    "id": "cmndobleg0001js6xa5qnt83t",
    "dayIdx": 0,
    "timeIdx": 0,
    "title": "Obstetri & Ginekologi",
    "color": "blue",
    "formattedTime": "13:15-15:15",
    "registrationTime": "13:05",
    "extra": null,
    "disabledDates": null,
    "statusOverride": null,
    "doctorId": "cmndobldf0000js6xdbpgturi"
  },
  {
    "id": "cmndobmbc001wjs6xavvm95jr",
    "dayIdx": 0,
    "timeIdx": 0,
    "title": "Saraf",
    "color": "emerald",
    "formattedTime": "15:00-18:00",
    "registrationTime": "13:00",
    "extra": null,
    "disabledDates": null,
    "statusOverride": null,
    "doctorId": "cmndobmaq001vjs6xhot4w0ry"
  },
  {
    "id": "cmndoblo8000kjs6xxt441rzg",
    "dayIdx": 2,
    "timeIdx": 0,
    "title": "Anak",
    "color": "emerald",
    "formattedTime": "08:30-13:00",
    "registrationTime": "07:30",
    "extra": null,
    "disabledDates": null,
    "statusOverride": null,
    "doctorId": "cmndoblmp000hjs6xvuue1gw8"
  },
  {
    "id": "cmndobm1g001cjs6x262dzhut",
    "dayIdx": 1,
    "timeIdx": 0,
    "title": "Penyakit Dalam",
    "color": "emerald",
    "formattedTime": "09:00-12:00",
    "registrationTime": "06:00",
    "extra": null,
    "disabledDates": null,
    "statusOverride": null,
    "doctorId": "cmndoblzx0019js6xoa7wqajj"
  },
  {
    "id": "cmndoblos000ljs6xj910wxd2",
    "dayIdx": 3,
    "timeIdx": 0,
    "title": "Anak",
    "color": "emerald",
    "formattedTime": "08:30-13:00",
    "registrationTime": "07:30",
    "extra": null,
    "disabledDates": null,
    "statusOverride": null,
    "doctorId": "cmndoblmp000hjs6xvuue1gw8"
  },
  {
    "id": "cmndoblp5000mjs6xd5hm0u88",
    "dayIdx": 4,
    "timeIdx": 0,
    "title": "Anak",
    "color": "emerald",
    "formattedTime": "08:30-13:00",
    "registrationTime": "07:30",
    "extra": null,
    "disabledDates": null,
    "statusOverride": null,
    "doctorId": "cmndoblmp000hjs6xvuue1gw8"
  },
  {
    "id": "cmndoblpt000njs6xmnvhjub0",
    "dayIdx": 5,
    "timeIdx": 0,
    "title": "Anak",
    "color": "emerald",
    "formattedTime": "08:30-13:00",
    "registrationTime": "07:30",
    "extra": null,
    "disabledDates": null,
    "statusOverride": null,
    "doctorId": "cmndoblmp000hjs6xvuue1gw8"
  },
  {
    "id": "cmndobm8u001sjs6x6nm577f9",
    "dayIdx": 1,
    "timeIdx": 0,
    "title": "Saraf",
    "color": "emerald",
    "formattedTime": "11:00-14:00",
    "registrationTime": "11:00",
    "extra": null,
    "disabledDates": null,
    "statusOverride": null,
    "doctorId": "cmndobm7x001rjs6xu53ths8y"
  },
  {
    "id": "cmndobma4001ujs6x3d44wlg8",
    "dayIdx": 5,
    "timeIdx": 0,
    "title": "Saraf",
    "color": "emerald",
    "formattedTime": "11:15-14:00",
    "registrationTime": "11:25",
    "extra": null,
    "disabledDates": null,
    "statusOverride": null,
    "doctorId": "cmndobm7x001rjs6xu53ths8y"
  },
  {
    "id": "cmndoblg60004js6x5v2kwawq",
    "dayIdx": 4,
    "timeIdx": 0,
    "title": "Obstetri & Ginekologi",
    "color": "blue",
    "formattedTime": "13:15-15:15",
    "registrationTime": "13:05",
    "extra": null,
    "disabledDates": null,
    "statusOverride": null,
    "doctorId": "cmndobldf0000js6xdbpgturi"
  },
  {
    "id": "cmndoblvl000zjs6x2v5msmpb",
    "dayIdx": 2,
    "timeIdx": 0,
    "title": "Bedah Umum",
    "color": "blue",
    "formattedTime": "06:00-07:30",
    "registrationTime": "06:00",
    "extra": null,
    "disabledDates": null,
    "statusOverride": null,
    "doctorId": "cmndoblt3000ujs6x1qraknzo"
  },
  {
    "id": "cmndoblwx0013js6x3n19w4v1",
    "dayIdx": 4,
    "timeIdx": 0,
    "title": "Bedah Umum",
    "color": "blue",
    "formattedTime": "06:00-07:30",
    "registrationTime": "06:00",
    "extra": null,
    "disabledDates": null,
    "statusOverride": null,
    "doctorId": "cmndoblt3000ujs6x1qraknzo"
  },
  {
    "id": "cmndobly60015js6x10mve1yr",
    "dayIdx": 5,
    "timeIdx": 0,
    "title": "Bedah Umum",
    "color": "blue",
    "formattedTime": "06:00-07:30",
    "registrationTime": "06:00",
    "extra": null,
    "disabledDates": null,
    "statusOverride": null,
    "doctorId": "cmndoblt3000ujs6x1qraknzo"
  },
  {
    "id": "cmndobm0k001ajs6x1az1ust8",
    "dayIdx": 0,
    "timeIdx": 0,
    "title": "Penyakit Dalam",
    "color": "emerald",
    "formattedTime": "09:00-12:00",
    "registrationTime": "06:00",
    "extra": null,
    "disabledDates": null,
    "statusOverride": null,
    "doctorId": "cmndoblzx0019js6xoa7wqajj"
  },
  {
    "id": "cmndobm22001ejs6xdy9u1hg0",
    "dayIdx": 2,
    "timeIdx": 0,
    "title": "Penyakit Dalam",
    "color": "emerald",
    "formattedTime": "09:00-12:00",
    "registrationTime": "06:00",
    "extra": null,
    "disabledDates": null,
    "statusOverride": null,
    "doctorId": "cmndoblzx0019js6xoa7wqajj"
  },
  {
    "id": "cmndobm2o001gjs6xqp5zzrfv",
    "dayIdx": 3,
    "timeIdx": 0,
    "title": "Penyakit Dalam",
    "color": "emerald",
    "formattedTime": "09:00-12:00",
    "registrationTime": "06:00",
    "extra": null,
    "disabledDates": null,
    "statusOverride": null,
    "doctorId": "cmndoblzx0019js6xoa7wqajj"
  },
  {
    "id": "cmndobm3n001ijs6x1wwd98qx",
    "dayIdx": 4,
    "timeIdx": 0,
    "title": "Penyakit Dalam",
    "color": "emerald",
    "formattedTime": "09:00-12:00",
    "registrationTime": "06:00",
    "extra": null,
    "disabledDates": null,
    "statusOverride": null,
    "doctorId": "cmndoblzx0019js6xoa7wqajj"
  },
  {
    "id": "cmndobm48001jjs6xn4msdao9",
    "dayIdx": 5,
    "timeIdx": 0,
    "title": "Penyakit Dalam",
    "color": "emerald",
    "formattedTime": "09:00-12:00",
    "registrationTime": "06:00",
    "extra": null,
    "disabledDates": null,
    "statusOverride": null,
    "doctorId": "cmndoblzx0019js6xoa7wqajj"
  },
  {
    "id": "cmndobm9m001tjs6xztqwlhzg",
    "dayIdx": 2,
    "timeIdx": 0,
    "title": "Saraf",
    "color": "emerald",
    "formattedTime": "11:00-14:00",
    "registrationTime": "11:00",
    "extra": null,
    "disabledDates": null,
    "statusOverride": null,
    "doctorId": "cmndobm7x001rjs6xu53ths8y"
  },
  {
    "id": "cmndobmbn001xjs6xtxwzynzl",
    "dayIdx": 3,
    "timeIdx": 0,
    "title": "Saraf",
    "color": "emerald",
    "formattedTime": "13:00-16:30",
    "registrationTime": "11:00",
    "extra": null,
    "disabledDates": null,
    "statusOverride": null,
    "doctorId": "cmndobmaq001vjs6xhot4w0ry"
  },
  {
    "id": "cmndobmby001yjs6xvnpximkx",
    "dayIdx": 4,
    "timeIdx": 0,
    "title": "Saraf",
    "color": "emerald",
    "formattedTime": "14:00-15:30",
    "registrationTime": "13:00",
    "extra": null,
    "disabledDates": null,
    "statusOverride": null,
    "doctorId": "cmndobmaq001vjs6xhot4w0ry"
  },
  {
    "id": "cmndobmdh0020js6x8rud06z5",
    "dayIdx": 0,
    "timeIdx": 0,
    "title": "Saraf",
    "color": "emerald",
    "formattedTime": "06:00-07:30",
    "registrationTime": "06:00",
    "extra": null,
    "disabledDates": null,
    "statusOverride": null,
    "doctorId": "cmndobmcm001zjs6x7d5gha01"
  },
  {
    "id": "cmndobmga0026js6xfl906f64",
    "dayIdx": 0,
    "timeIdx": 0,
    "title": "THT-KL",
    "color": "blue",
    "formattedTime": "14:00-18:00",
    "registrationTime": "13:00",
    "extra": null,
    "disabledDates": null,
    "statusOverride": null,
    "doctorId": "cmndobmfn0025js6xjq03oow2"
  },
  {
    "id": "cmndobmgx0027js6xxw73wgia",
    "dayIdx": 1,
    "timeIdx": 0,
    "title": "THT-KL",
    "color": "blue",
    "formattedTime": "08:00-12:00",
    "registrationTime": "07:00",
    "extra": null,
    "disabledDates": null,
    "statusOverride": null,
    "doctorId": "cmndobmfn0025js6xjq03oow2"
  },
  {
    "id": "cmndobmh70028js6xy7xq5pi0",
    "dayIdx": 2,
    "timeIdx": 0,
    "title": "THT-KL",
    "color": "blue",
    "formattedTime": "14:00-18:00",
    "registrationTime": "13:00",
    "extra": null,
    "disabledDates": null,
    "statusOverride": null,
    "doctorId": "cmndobmfn0025js6xjq03oow2"
  },
  {
    "id": "cmndobmht0029js6xppmu3xyp",
    "dayIdx": 3,
    "timeIdx": 0,
    "title": "THT-KL",
    "color": "blue",
    "formattedTime": "08:00-12:00",
    "registrationTime": "07:00",
    "extra": null,
    "disabledDates": null,
    "statusOverride": null,
    "doctorId": "cmndobmfn0025js6xjq03oow2"
  },
  {
    "id": "cmndobmi6002ajs6xyy0tjneh",
    "dayIdx": 4,
    "timeIdx": 0,
    "title": "THT-KL",
    "color": "blue",
    "formattedTime": "13:00-15:00",
    "registrationTime": "12:00",
    "extra": null,
    "disabledDates": null,
    "statusOverride": null,
    "doctorId": "cmndobmfn0025js6xjq03oow2"
  },
  {
    "id": "cmndobmpi002rjs6xbozedets",
    "dayIdx": 4,
    "timeIdx": 0,
    "title": "Paru",
    "color": "emerald",
    "formattedTime": "10:00-12:00",
    "registrationTime": "09:00",
    "extra": null,
    "disabledDates": null,
    "statusOverride": null,
    "doctorId": "cmndobmne002mjs6xecyx4a8b"
  },
  {
    "id": "cmndobmr3002ujs6xtsebyf80",
    "dayIdx": 0,
    "timeIdx": 0,
    "title": "Orthopaedi",
    "color": "blue",
    "formattedTime": "08:00-10:30",
    "registrationTime": "07:00",
    "extra": null,
    "disabledDates": null,
    "statusOverride": null,
    "doctorId": "cmndobmqf002tjs6xdkog9yct"
  },
  {
    "id": "cmndobmrd002vjs6xaqjcy5sj",
    "dayIdx": 2,
    "timeIdx": 0,
    "title": "Orthopaedi",
    "color": "blue",
    "formattedTime": "08:00-09:30",
    "registrationTime": "07:00",
    "extra": null,
    "disabledDates": null,
    "statusOverride": null,
    "doctorId": "cmndobmqf002tjs6xdkog9yct"
  },
  {
    "id": "cmndobmsb002yjs6xce8r30jg",
    "dayIdx": 1,
    "timeIdx": 0,
    "title": "Bedah Umum",
    "color": "blue",
    "formattedTime": "08:00-12:00",
    "registrationTime": "07:00",
    "extra": null,
    "disabledDates": null,
    "statusOverride": null,
    "doctorId": "cmndobms0002xjs6x0p1q6mfw"
  },
  {
    "id": "cmndobmsz002zjs6xz8ri8tj6",
    "dayIdx": 4,
    "timeIdx": 0,
    "title": "Bedah Umum",
    "color": "blue",
    "formattedTime": "14:05-17:00",
    "registrationTime": "13:05",
    "extra": null,
    "disabledDates": null,
    "statusOverride": null,
    "doctorId": "cmndobms0002xjs6x0p1q6mfw"
  },
  {
    "id": "cmndobmvp0034js6xpikcm72u",
    "dayIdx": 5,
    "timeIdx": 0,
    "title": "Jantung",
    "color": "emerald",
    "formattedTime": "08:00-14:00",
    "registrationTime": "07:00",
    "extra": null,
    "disabledDates": null,
    "statusOverride": null,
    "doctorId": "cmndobmtv0031js6xken9w41w"
  },
  {
    "id": "cmndobmwn0036js6xtmr5fzo9",
    "dayIdx": 0,
    "timeIdx": 0,
    "title": "Umum",
    "color": "emerald",
    "formattedTime": "07:30-09:15",
    "registrationTime": "06:30",
    "extra": null,
    "disabledDates": null,
    "statusOverride": null,
    "doctorId": "cmndobmw00035js6xmofr21xr"
  },
  {
    "id": "cmndobmx90038js6x2igaplrk",
    "dayIdx": 2,
    "timeIdx": 0,
    "title": "Umum",
    "color": "emerald",
    "formattedTime": "07:30-09:15",
    "registrationTime": "06:30",
    "extra": null,
    "disabledDates": null,
    "statusOverride": null,
    "doctorId": "cmndobmw00035js6xmofr21xr"
  },
  {
    "id": "cmndobn1a003hjs6xivmqtp57",
    "dayIdx": 0,
    "timeIdx": 0,
    "title": "Mata",
    "color": "blue",
    "formattedTime": "07:00-08:00",
    "registrationTime": "06:00",
    "extra": "(Khusus PACHO)",
    "disabledDates": null,
    "statusOverride": null,
    "doctorId": "cmndobn0y003gjs6xsmt9ec1k"
  },
  {
    "id": "cmndobn33003ljs6xlqbvn21q",
    "dayIdx": 4,
    "timeIdx": 0,
    "title": "Mata",
    "color": "blue",
    "formattedTime": "07:00-08:00",
    "registrationTime": "06:00",
    "extra": "(Khusus operasi)",
    "disabledDates": null,
    "statusOverride": null,
    "doctorId": "cmndobn0y003gjs6xsmt9ec1k"
  },
  {
    "id": "cmndobmf60024js6x46k6sbqz",
    "dayIdx": 5,
    "timeIdx": 0,
    "title": "THT-KL",
    "color": "blue",
    "formattedTime": "13:00-15:00",
    "registrationTime": "13:00",
    "extra": null,
    "disabledDates": null,
    "statusOverride": null,
    "doctorId": "cmndobmef0022js6xjynhu8k4"
  },
  {
    "id": "cmndobmj2002cjs6xiubsa2sw",
    "dayIdx": 0,
    "timeIdx": 0,
    "title": "Urologi",
    "color": "blue",
    "formattedTime": "18:00-21:00",
    "registrationTime": "16:00",
    "extra": null,
    "disabledDates": null,
    "statusOverride": null,
    "doctorId": "cmndobmir002bjs6xpoc9wjwa"
  },
  {
    "id": "cmndobmwy0037js6xxdvtfchn",
    "dayIdx": 1,
    "timeIdx": 0,
    "title": "Umum",
    "color": "emerald",
    "formattedTime": "07:30-09:15",
    "registrationTime": "06:45",
    "extra": null,
    "disabledDates": null,
    "statusOverride": null,
    "doctorId": "cmndobmw00035js6xmofr21xr"
  },
  {
    "id": "cmndobmtj0030js6x2am1nuzx",
    "dayIdx": 5,
    "timeIdx": 0,
    "title": "Bedah Umum",
    "color": "blue",
    "formattedTime": "15:00-18:00",
    "registrationTime": "13:00",
    "extra": null,
    "disabledDates": null,
    "statusOverride": null,
    "doctorId": "cmndobms0002xjs6x0p1q6mfw"
  },
  {
    "id": "cmndobmuh0032js6xdsg2hzxk",
    "dayIdx": 1,
    "timeIdx": 0,
    "title": "Jantung",
    "color": "emerald",
    "formattedTime": "14:30-18:00",
    "registrationTime": "13:00",
    "extra": null,
    "disabledDates": null,
    "statusOverride": null,
    "doctorId": "cmndobmtv0031js6xken9w41w"
  },
  {
    "id": "cmndobmom002ojs6x1ifbao5w",
    "dayIdx": 1,
    "timeIdx": 0,
    "title": "Paru",
    "color": "emerald",
    "formattedTime": "13:00-15:00",
    "registrationTime": "11:00",
    "extra": null,
    "disabledDates": null,
    "statusOverride": null,
    "doctorId": "cmndobmne002mjs6xecyx4a8b"
  },
  {
    "id": "cmndobmkx002gjs6xfhfpi2my",
    "dayIdx": 0,
    "timeIdx": 0,
    "title": "Orthopaedi",
    "color": "blue",
    "formattedTime": "11:00-12:15",
    "registrationTime": "10:00",
    "extra": null,
    "disabledDates": null,
    "statusOverride": null,
    "doctorId": "cmndobmka002fjs6x4ngwvp5w"
  },
  {
    "id": "cmndobml7002hjs6xgvap5q9k",
    "dayIdx": 1,
    "timeIdx": 0,
    "title": "Orthopaedi",
    "color": "blue",
    "formattedTime": "11:00-12:15",
    "registrationTime": "09:00",
    "extra": null,
    "disabledDates": null,
    "statusOverride": null,
    "doctorId": "cmndobmka002fjs6x4ngwvp5w"
  },
  {
    "id": "cmndobmrp002wjs6x3cjlogt6",
    "dayIdx": 5,
    "timeIdx": 0,
    "title": "Orthopaedi",
    "color": "blue",
    "formattedTime": "08:00-10:30",
    "registrationTime": "07:00",
    "extra": "odd_weeks",
    "disabledDates": null,
    "statusOverride": null,
    "doctorId": "cmndobmqf002tjs6xdkog9yct"
  },
  {
    "id": "cmndobmo0002njs6xof36lbkm",
    "dayIdx": 0,
    "timeIdx": 0,
    "title": "Paru",
    "color": "emerald",
    "formattedTime": "13:00-15:00",
    "registrationTime": "11:00",
    "extra": null,
    "disabledDates": null,
    "statusOverride": null,
    "doctorId": "cmndobmne002mjs6xecyx4a8b"
  },
  {
    "id": "cmndobmjn002djs6x77wmqr63",
    "dayIdx": 2,
    "timeIdx": 0,
    "title": "Urologi",
    "color": "blue",
    "formattedTime": "18:00-21:00",
    "registrationTime": "16:00",
    "extra": null,
    "disabledDates": null,
    "statusOverride": null,
    "doctorId": "cmndobmir002bjs6xpoc9wjwa"
  },
  {
    "id": "cmndobmyi003bjs6x3geb8tnp",
    "dayIdx": 1,
    "timeIdx": 0,
    "title": "Jiwa",
    "color": "emerald",
    "formattedTime": "15:15-17:15",
    "registrationTime": "13:00",
    "extra": null,
    "disabledDates": null,
    "statusOverride": null,
    "doctorId": "cmndobmxv0039js6xfhs3tvow"
  },
  {
    "id": "cmndobn2i003jjs6xa5pspx0g",
    "dayIdx": 2,
    "timeIdx": 0,
    "title": "Mata",
    "color": "blue",
    "formattedTime": "07:00-10:00",
    "registrationTime": "06:00",
    "extra": null,
    "disabledDates": null,
    "statusOverride": null,
    "doctorId": "cmndobn0y003gjs6xsmt9ec1k"
  },
  {
    "id": "cmndobn2t003kjs6ximr6kmvo",
    "dayIdx": 3,
    "timeIdx": 0,
    "title": "Mata",
    "color": "blue",
    "formattedTime": "07:00-10:00",
    "registrationTime": "06:00",
    "extra": null,
    "disabledDates": null,
    "statusOverride": null,
    "doctorId": "cmndobn0y003gjs6xsmt9ec1k"
  },
  {
    "id": "cmndobmy6003ajs6xk4q4x99v",
    "dayIdx": 0,
    "timeIdx": 0,
    "title": "Jiwa",
    "color": "emerald",
    "formattedTime": "15:15-17:15",
    "registrationTime": "13:00",
    "extra": null,
    "disabledDates": null,
    "statusOverride": null,
    "doctorId": "cmndobmxv0039js6xfhs3tvow"
  },
  {
    "id": "cmndobmdu0021js6xi8nu5zp9",
    "dayIdx": 2,
    "timeIdx": 0,
    "title": "Saraf",
    "color": "emerald",
    "formattedTime": "07:30-09:29",
    "registrationTime": "06:30",
    "extra": null,
    "disabledDates": null,
    "statusOverride": null,
    "doctorId": "cmndobmcm001zjs6x7d5gha01"
  },
  {
    "id": "cmndobmjz002ejs6xej4yvsnw",
    "dayIdx": 4,
    "timeIdx": 0,
    "title": "Urologi",
    "color": "blue",
    "formattedTime": "18:00-22:00",
    "registrationTime": "16:00",
    "extra": null,
    "disabledDates": null,
    "statusOverride": null,
    "doctorId": "cmndobmir002bjs6xpoc9wjwa"
  },
  {
    "id": "cmndobmm5002jjs6xl2otr40x",
    "dayIdx": 3,
    "timeIdx": 0,
    "title": "Orthopaedi",
    "color": "blue",
    "formattedTime": "11:00-12:15",
    "registrationTime": "09:00",
    "extra": null,
    "disabledDates": null,
    "statusOverride": null,
    "doctorId": "cmndobmka002fjs6x4ngwvp5w"
  },
  {
    "id": "cmndobmmf002kjs6x97e34uiq",
    "dayIdx": 4,
    "timeIdx": 0,
    "title": "Orthopaedi",
    "color": "blue",
    "formattedTime": "11:00-12:15",
    "registrationTime": "09:00",
    "extra": null,
    "disabledDates": null,
    "statusOverride": null,
    "doctorId": "cmndobmka002fjs6x4ngwvp5w"
  },
  {
    "id": "cmndobmow002pjs6xdabpop3u",
    "dayIdx": 2,
    "timeIdx": 0,
    "title": "Paru",
    "color": "emerald",
    "formattedTime": "13:00-15:00",
    "registrationTime": "11:00",
    "extra": null,
    "disabledDates": null,
    "statusOverride": null,
    "doctorId": "cmndobmne002mjs6xecyx4a8b"
  },
  {
    "id": "cmndobmp8002qjs6x8uw4khxm",
    "dayIdx": 3,
    "timeIdx": 0,
    "title": "Paru",
    "color": "emerald",
    "formattedTime": "13:00-15:00",
    "registrationTime": "11:00",
    "extra": null,
    "disabledDates": null,
    "statusOverride": null,
    "doctorId": "cmndobmne002mjs6xecyx4a8b"
  },
  {
    "id": "cmndobmpu002sjs6xuh26mwn3",
    "dayIdx": 5,
    "timeIdx": 0,
    "title": "Paru",
    "color": "emerald",
    "formattedTime": "13:00-15:00",
    "registrationTime": "11:00",
    "extra": null,
    "disabledDates": null,
    "statusOverride": null,
    "doctorId": "cmndobmne002mjs6xecyx4a8b"
  },
  {
    "id": "cmndobmz8003cjs6x960edsn0",
    "dayIdx": 3,
    "timeIdx": 0,
    "title": "Jiwa",
    "color": "emerald",
    "formattedTime": "15:15-17:15",
    "registrationTime": "13:00",
    "extra": null,
    "disabledDates": null,
    "statusOverride": null,
    "doctorId": "cmndobmxv0039js6xfhs3tvow"
  },
  {
    "id": "cmndobmzp003djs6xok2y7gw8",
    "dayIdx": 4,
    "timeIdx": 0,
    "title": "Jiwa",
    "color": "emerald",
    "formattedTime": "14:45-17:15",
    "registrationTime": "13:00",
    "extra": null,
    "disabledDates": null,
    "statusOverride": null,
    "doctorId": "cmndobmxv0039js6xfhs3tvow"
  },
  {
    "id": "cmndobn0n003fjs6xfj60dd3o",
    "dayIdx": 2,
    "timeIdx": 0,
    "title": "Konservasi Gigi",
    "color": "emerald",
    "formattedTime": "15:00-18:00",
    "registrationTime": "06:00",
    "extra": null,
    "disabledDates": null,
    "statusOverride": null,
    "doctorId": "cmndobn01003ejs6xa72q1txb"
  },
  {
    "id": "cmndobn1x003ijs6x9entbosh",
    "dayIdx": 1,
    "timeIdx": 0,
    "title": "Mata",
    "color": "blue",
    "formattedTime": "07:00-10:00",
    "registrationTime": "06:00",
    "extra": null,
    "disabledDates": null,
    "statusOverride": null,
    "doctorId": "cmndobn0y003gjs6xsmt9ec1k"
  },
  {
    "id": "cmndobn3p003njs6x34sh32au",
    "dayIdx": 0,
    "timeIdx": 0,
    "title": "Rehab Medik",
    "color": "emerald",
    "formattedTime": "11:30-14:00",
    "registrationTime": "11:00",
    "extra": null,
    "disabledDates": null,
    "statusOverride": null,
    "doctorId": "cmndobn3f003mjs6xk8y6zhtf"
  },
  {
    "id": "cmndobn41003ojs6xlzmeox5g",
    "dayIdx": 1,
    "timeIdx": 0,
    "title": "Rehab Medik",
    "color": "emerald",
    "formattedTime": "12:15-14:00",
    "registrationTime": "11:00",
    "extra": null,
    "disabledDates": null,
    "statusOverride": null,
    "doctorId": "cmndobn3f003mjs6xk8y6zhtf"
  },
  {
    "id": "cmndobn4p003pjs6xrl3rbmum",
    "dayIdx": 2,
    "timeIdx": 0,
    "title": "Rehab Medik",
    "color": "emerald",
    "formattedTime": "11:30-14:00",
    "registrationTime": "11:00",
    "extra": null,
    "disabledDates": null,
    "statusOverride": null,
    "doctorId": "cmndobn3f003mjs6xk8y6zhtf"
  },
  {
    "id": "cmndobn5a003qjs6xioj4j2vk",
    "dayIdx": 3,
    "timeIdx": 0,
    "title": "Rehab Medik",
    "color": "emerald",
    "formattedTime": "11:30-14:00",
    "registrationTime": "11:00",
    "extra": null,
    "disabledDates": null,
    "statusOverride": null,
    "doctorId": "cmndobn3f003mjs6xk8y6zhtf"
  },
  {
    "id": "cmndobmv30033js6x2akpkliy",
    "dayIdx": 3,
    "timeIdx": 0,
    "title": "Jantung",
    "color": "emerald",
    "formattedTime": "14:30-18:00",
    "registrationTime": "13:30",
    "extra": null,
    "disabledDates": [],
    "statusOverride": null,
    "doctorId": "cmndobmtv0031js6xken9w41w"
  },
  {
    "id": "cmndobmep0023js6xc5sx0ivw",
    "dayIdx": 3,
    "timeIdx": 0,
    "title": "THT-KL",
    "color": "blue",
    "formattedTime": "16:00-18:00",
    "registrationTime": "15:00",
    "extra": null,
    "disabledDates": null,
    "statusOverride": null,
    "doctorId": "cmndobmef0022js6xjynhu8k4"
  },
  {
    "id": "cmndobmlk002ijs6xktk1u3fm",
    "dayIdx": 2,
    "timeIdx": 0,
    "title": "Orthopaedi",
    "color": "rose",
    "formattedTime": "07:00-08:00",
    "registrationTime": "06:00",
    "extra": "(Khusus operasi)",
    "disabledDates": null,
    "statusOverride": "OPERASI",
    "doctorId": "cmndobmka002fjs6x4ngwvp5w"
  },
  {
    "id": "cmndobmn2002ljs6xdcpmtqs5",
    "dayIdx": 5,
    "timeIdx": 0,
    "title": "Orthopaedi",
    "color": "blue",
    "formattedTime": "11:00-12:15",
    "registrationTime": "09:00",
    "extra": "even_weeks",
    "disabledDates": null,
    "statusOverride": null,
    "doctorId": "cmndobmka002fjs6x4ngwvp5w"
  },
  {
    "id": "cmndobnft004cjs6xj06t6776",
    "dayIdx": 1,
    "timeIdx": 0,
    "title": "Urologi",
    "color": "blue",
    "formattedTime": "19:00-21:00",
    "registrationTime": "16:00",
    "extra": null,
    "disabledDates": null,
    "statusOverride": null,
    "doctorId": "cmndobnf5004bjs6xndgzlmfg"
  },
  {
    "id": "cmndobngf004djs6xv5ygr6dj",
    "dayIdx": 3,
    "timeIdx": 0,
    "title": "Urologi",
    "color": "blue",
    "formattedTime": "19:00-21:00",
    "registrationTime": "16:00",
    "extra": null,
    "disabledDates": null,
    "statusOverride": null,
    "doctorId": "cmndobnf5004bjs6xndgzlmfg"
  },
  {
    "id": "cmndobngz004ejs6xt1zpedvi",
    "dayIdx": 5,
    "timeIdx": 0,
    "title": "Urologi",
    "color": "blue",
    "formattedTime": "12:00-15:00",
    "registrationTime": "11:00",
    "extra": null,
    "disabledDates": null,
    "statusOverride": null,
    "doctorId": "cmndobnf5004bjs6xndgzlmfg"
  },
  {
    "id": "cmndobley0002js6xckfl34sb",
    "dayIdx": 1,
    "timeIdx": 0,
    "title": "Obstetri & Ginekologi",
    "color": "blue",
    "formattedTime": "13:15-15:15",
    "registrationTime": "13:05",
    "extra": null,
    "disabledDates": null,
    "statusOverride": null,
    "doctorId": "cmndobldf0000js6xdbpgturi"
  },
  {
    "id": "cmnfmnfza000d3wrloq3hl96g",
    "dayIdx": 4,
    "timeIdx": 0,
    "title": "Praktek",
    "color": "blue",
    "formattedTime": "12:00-15:00",
    "registrationTime": "11:00",
    "extra": null,
    "disabledDates": null,
    "statusOverride": null,
    "doctorId": "cmnfmipdy000fa4rlpszyztyb"
  },
  {
    "id": "cmnfmnsu6000i7orllzu167yz",
    "dayIdx": 5,
    "timeIdx": 0,
    "title": "Praktek",
    "color": "blue",
    "formattedTime": "11:00-14:00",
    "registrationTime": "14:00",
    "extra": null,
    "disabledDates": null,
    "statusOverride": null,
    "doctorId": "cmnfmipdy000fa4rlpszyztyb"
  },
  {
    "id": "cmnfmtla6000ga4rl2rjvxvjq",
    "dayIdx": 0,
    "timeIdx": 0,
    "title": "Praktek",
    "color": "blue",
    "formattedTime": "18:00-20:00",
    "registrationTime": "10:30",
    "extra": null,
    "disabledDates": null,
    "statusOverride": null,
    "doctorId": "cmnfmqabu000j7orlwkwv758l"
  }
]